Metadata-Version: 2.1
Name: naif
Version: 0.1.1
Summary: Numerical Analysis and Integer combinations of Frequencies
Author: Leandro Beraldo e Silva
Author-email: lberaldoesilva@gmail.com
License: MIT
Requires-Python: >=3
License-File: LICENSE
